nif_validator/__init__.py
nif_validator/validator.py
NIF_validator-0.0.6.dist-info/LICENSE
NIF_validator-0.0.6.dist-info/METADATA
NIF_validator-0.0.6.dist-info/WHEEL
NIF_validator-0.0.6.dist-info/top_level.txt
NIF_validator-0.0.6.dist-info/RECORD
