Metadata-Version: 2.1
Name: NIF-validator
Version: 0.0.6
Summary: A small Python package to validate Portuguese taxpayer numbers (NIFs)
Home-page: https://github.com/spamz23/NIF-validator
Author: Diogo Silva
Author-email: diogo_silva30@hotmail.com
License: MIT
Platform: UNKNOWN
Classifier: Programming Language :: Python :: 3
Classifier: License :: OSI Approved :: MIT License
Classifier: Operating System :: OS Independent
Requires-Python: >=3.9
Requires-Dist: requests (==2.24.0)
Requires-Dist: beautifulsoup4 (==4.9.3)
